CHANGES.rst
CONTRIBUTORS.rst
DEVELOP.rst
LICENSE.rst
MANIFEST.in
README.rst
setup.cfg
setup.py
docs/conf.py
docs/index.rst
src/lapis/.DS_Store
src/lapis/__init__.py
src/lapis.member.egg-info/PKG-INFO
src/lapis.member.egg-info/SOURCES.txt
src/lapis.member.egg-info/dependency_links.txt
src/lapis.member.egg-info/entry_points.txt
src/lapis.member.egg-info/namespace_packages.txt
src/lapis.member.egg-info/not-zip-safe
src/lapis.member.egg-info/requires.txt
src/lapis.member.egg-info/top_level.txt
src/lapis/member/.DS_Store
src/lapis/member/__init__.py
src/lapis/member/configure.zcml
src/lapis/member/interfaces.py
src/lapis/member/permissions.zcml
src/lapis/member/setuphandlers.py
src/lapis/member/testing.py
src/lapis/member/browser/__init__.py
src/lapis/member/browser/configure.zcml
src/lapis/member/browser/overrides/.gitkeep
src/lapis/member/browser/static/.gitkeep
src/lapis/member/content/.DS_Store
src/lapis/member/content/__init__.py
src/lapis/member/content/forum_page.py
src/lapis/member/content/forum_page.xml
src/lapis/member/locales/README.rst
src/lapis/member/locales/__init__.py
src/lapis/member/locales/lapis.member.pot
src/lapis/member/locales/update.py
src/lapis/member/locales/update.sh
src/lapis/member/locales/en/LC_MESSAGES/lapis.member.mo
src/lapis/member/locales/en/LC_MESSAGES/lapis.member.po
src/lapis/member/profiles/.DS_Store
src/lapis/member/profiles/default/.DS_Store
src/lapis/member/profiles/default/browserlayer.xml
src/lapis/member/profiles/default/catalog.xml
src/lapis/member/profiles/default/metadata.xml
src/lapis/member/profiles/default/registry.xml
src/lapis/member/profiles/default/rolemap.xml
src/lapis/member/profiles/default/types.xml
src/lapis/member/profiles/default/workflows.xml
src/lapis/member/profiles/default/types/Forum_Page.xml
src/lapis/member/profiles/default/workflows/.DS_Store
src/lapis/member/profiles/default/workflows/forum_page_workflow/definition.xml
src/lapis/member/profiles/uninstall/browserlayer.xml
src/lapis/member/tests/__init__.py
src/lapis/member/tests/test_ct_forum_page.py
src/lapis/member/tests/test_robot.py
src/lapis/member/tests/test_setup.py
src/lapis/member/tests/robot/test_ct_forum_page.robot
src/lapis/member/tests/robot/test_example.robot