Metadata-Version: 1.2
Name: lapis.member
Version: 1.0a1
Summary: Content type and workflow for Plone
Home-page: https://github.com/collective/lapis.member
Author: Espen Moe-Nilssen
Author-email: espen@medialog.no
License: GPL version 2
Project-URL: Source, https://github.com/collective/lapis.member
Project-URL: Tracker, https://github.com/collective/lapis.member/issues
Project-URL: PyPI, https://pypi.python.org/pypi/lapis.member
Keywords: Python Plone
Platform: UNKNOWN
Classifier: Environment :: Web Environment
Classifier: Framework :: Plone
Classifier: Framework :: Plone :: Addon
Classifier: Framework :: Plone :: 5.1
Classifier: Programming Language :: Python
Classifier: Programming Language :: Python :: 2.7
Classifier: Operating System :: OS Independent
Classifier: License :: OSI Approved :: GNU General Public License v2 (GPLv2)
Requires-Python: ==2.7
